Metadata-Version: 2.4
Name: bach-virtual_number
Version: 1.0.0
Summary: RapidAPI: shameeraanuranga1991/virtual-number
Project-URL: Homepage, https://github.com/bachstudio/bach-virtual_number
Project-URL: Repository, https://github.com/bachstudio/bach-virtual_number
Project-URL: Documentation, https://github.com/bachstudio/bach-virtual_number#readme
Requires-Python: >=3.10
Requires-Dist: fastmcp>=2.0.0
Requires-Dist: httpx>=0.25.0
Provides-Extra: dev
Requires-Dist: black>=23.0.0; extra == 'dev'
Requires-Dist: pytest>=7.0.0; extra == 'dev'
